LICENSE
README.md
setup.py
negpipi_ceu/--init.py
negpipi_ceu/monitor.py
negpipi_ceu/video.py
negpipi_ceu.egg-info/PKG-INFO
negpipi_ceu.egg-info/SOURCES.txt
negpipi_ceu.egg-info/dependency_links.txt
negpipi_ceu.egg-info/top_level.txt