Metadata-Version: 2.1
Name: negpipi-ceu
Version: 0.0.1
Summary: isso é apenas um teste
Author: Sidemar
Author-email: sidmar.88@hotmail.com
License: MIT License
Keywords: neceu
License-File: LICENSE
